Workbook

Sheet Instrucoes
A1: Simulador de Perfil do Cliente — Projeção de Resultados
A3: Como usar esta planilha:
A4: 1. Vá até a aba 'Perfil_Risco' e responda as 4 perguntas (células azuis com lista suspensa).
A5: 2. Vá até a aba 'Dados_Cliente' e preencha os dados em azul (nome, idade, renda, valores e prazo).
A6: 3. Vá até a aba 'Resultado' para ver a projeção final, os indicadores e os gráficos.
A7: 4. Se quiser, ajuste as premissas de mercado (retorno/risco/inflação) na aba 'Mercado'.
A9: Células AZUIS = você pode editar. Células PRETAS = calculadas automaticamente, não edite.
A10: Prazo máximo suportado por esta planilha: 30 anos.

Sheet Mercado
A1: Premissas de Mercado (edite os valores em azul)
A3: Código | B3: Classe de Ativo | C3: Retorno Anual Esperado | D3: Volatilidade Anual | E3: Fonte / Observação
A4: renda_fixa_pos | B4: Renda Fixa Pós-fixada (CDI / Tesouro Selic) | C4: 0.105 | D4: 0.02 | E4: Estimativa própria — ajustar conforme fonte oficial
A5: renda_fixa_pre | B5: Renda Fixa Prefixada / Inflação | C5: 0.095 | D5: 0.06 | E5: Estimativa própria — ajustar conforme fonte oficial
A6: multimercado | B6: Fundos Multimercado | C6: 0.12 | D6: 0.09 | E6: Estimativa própria — ajustar conforme fonte oficial
A7: acoes_br | B7: Ações Brasil | C7: 0.15 | D7: 0.22 | E7: Estimativa própria — ajustar conforme fonte oficial
A8: acoes_global | B8: Ações Globais | C8: 0.13 | D8: 0.18 | E8: Estimativa própria — ajustar conforme fonte oficial
A9: fundos_imobiliarios | B9: Fundos Imobiliários (FIIs) | C9: 0.11 | D9: 0.13 | E9: Estimativa própria — ajustar conforme fonte oficial
A11: Inflação anual esperada (IPCA) | B11: 0.045
A12: Taxa livre de risco (CDI / Selic) | B12: 0.105
A14: Fonte sugerida para atualização: Banco Central do Brasil (bcb.gov.br) para CDI/Selic, e IBGE (ibge.gov.br/explica/inflacao.php) para o IPCA.

Sheet Alocacao_Modelo
A1: Alocação-modelo por Perfil de Risco (% da carteira)
A3: Perfil | B3: renda_fixa_pos | C3: renda_fixa_pre | D3: multimercado | E3: acoes_br | F3: acoes_global | G3: fundos_imobiliarios
A4: conservador | B4: 0.6 | C4: 0.3 | D4: 0.1 | E4: 0 | F4: 0 | G4: 0
A5: moderado | B5: 0.35 | C5: 0.2 | D5: 0.2 | E5: 0.1 | F5: 0 | G5: 0.15
A6: arrojado | B6: 0.15 | C6: 0 | D6: 0.2 | E6: 0.3 | F6: 0.2 | G6: 0.15

Sheet Perfil_Risco
A1: Questionário de Perfil de Risco (Suitability)
H2: Preservar o capital, evitando perdas | I2: 1
A3: Pergunta | B3: Sua resposta (selecione) | C3: Pontuação | H3: Obter renda com baixo risco | I3: 2
A4: Qual seu objetivo principal com os investimentos? | B4: Preservar o capital, evitando perdas | C4: =IFERROR(VLOOKUP(B4,$H$2:$I$5,2,FALSE),0) -> 1 | H4: Crescimento do patrimônio no médio prazo | I4: 3
A5: Qual seu horizonte de investimento? | B5: Até 1 ano | C5: =IFERROR(VLOOKUP(B5,$H$7:$I$10,2,FALSE),0) -> 1 | H5: Maximizar retorno, aceitando oscilações | I5: 4
A6: Se sua carteira caísse 15% em um mês, você: | B6: Resgataria tudo imediatamente | C6: =IFERROR(VLOOKUP(B6,$H$12:$I$15,2,FALSE),0) -> 1
A7: Qual sua experiência com investimentos de risco (ações, fundos)? | B7: Nenhuma experiência | C7: =IFERROR(VLOOKUP(B7,$H$17:$I$20,2,FALSE),0) -> 1 | H7: Até 1 ano | I7: 1
H8: De 1 a 3 anos | I8: 2
A9: Pontuação total | B9: =SUM(C4:C7) -> 4 | H9: De 3 a 7 anos | I9: 3
A10: Perfil identificado | B10: =IF(B9<=7,"conservador",IF(B9<=12,"moderado","arrojado")) -> conservador | H10: Mais de 7 anos | I10: 4
H12: Resgataria tudo imediatamente | I12: 1
H13: Resgataria parte do valor | I13: 2
H14: Manteria o investimento | I14: 3
H15: Aproveitaria para investir mais | I15: 4
H17: Nenhuma experiência | I17: 1
H18: Pouca experiência | I18: 2
H19: Experiência moderada | I19: 3
H20: Bastante experiência | I20: 4

Sheet Dados_Cliente
A1: Dados do Cliente
A3: Nome | B3: matheus
A4: Idade | B4: 24
A5: Renda mensal (R$) | B5: 4000
A6: Valor inicial disponível (R$) | B6: 100
A7: Aporte mensal planejado (R$) | B7: 100
A8: Prazo do investimento (anos, máx. 30) | B8: 1
A10: Perfil de risco (do questionário) | B10: =Perfil_Risco!B10 -> conservador
A12: Alocação atual da carteira (conforme perfil)
A13: Classe de Ativo | B13: Peso (%)
A14: =Mercado!B4 -> Renda Fixa Pós-fixada (CDI / Tesouro Selic) | B14: =INDEX(Alocacao_Modelo!$B$4:$G$6,MATCH($B$10,Alocacao_Modelo!$A$4:$A$6,0),1) -> 0.6
A15: =Mercado!B5 -> Renda Fixa Prefixada / Inflação | B15: =INDEX(Alocacao_Modelo!$B$4:$G$6,MATCH($B$10,Alocacao_Modelo!$A$4:$A$6,0),2) -> 0.3
A16: =Mercado!B6 -> Fundos Multimercado | B16: =INDEX(Alocacao_Modelo!$B$4:$G$6,MATCH($B$10,Alocacao_Modelo!$A$4:$A$6,0),3) -> 0.1
A17: =Mercado!B7 -> Ações Brasil | B17: =INDEX(Alocacao_Modelo!$B$4:$G$6,MATCH($B$10,Alocacao_Modelo!$A$4:$A$6,0),4) -> 0
A18: =Mercado!B8 -> Ações Globais | B18: =INDEX(Alocacao_Modelo!$B$4:$G$6,MATCH($B$10,Alocacao_Modelo!$A$4:$A$6,0),5) -> 0
A19: =Mercado!B9 -> Fundos Imobiliários (FIIs) | B19: =INDEX(Alocacao_Modelo!$B$4:$G$6,MATCH($B$10,Alocacao_Modelo!$A$4:$A$6,0),6) -> 0
A21: Retorno anual estimado da carteira | B21: =SUMPRODUCT(B14:B19,Mercado!C4:C9) -> 0.1035
A22: Volatilidade anual estimada da carteira | B22: =SUMPRODUCT(B14:B19,Mercado!D4:D9) -> 0.039
A24: Taxa mensal — cenário esperado | B24: =(1+B21)^(1/12)-1 -> 0.0082410173
A25: Retorno anual — cenário otimista (aprox. percentil 90) | B25: =B21+1.2816*B22 -> 0.1534824
A26: Retorno anual — cenário pessimista (aprox. percentil 10, piso -30%) | B26: =MAX(B21-1.2816*B22,-0.3) -> 0.0535176
A27: Taxa mensal — cenário otimista | B27: =(1+B25)^(1/12)-1 -> 0.011969867
A28: Taxa mensal — cenário pessimista | B28: =(1+B26)^(1/12)-1 -> 0.0043540063

Sheet Resultado
A1: Resultado da Projeção
A3: Cliente | B3: =Dados_Cliente!B3 -> matheus
A4: Perfil de risco | B4: =Dados_Cliente!B10 -> conservador
A5: Retorno anual estimado da carteira | B5: =Dados_Cliente!B21 -> 0.1035
A6: Prazo (anos) | B6: =Dados_Cliente!B8 -> 1
A7: Total investido (aportes + inicial) | B7: =INDEX(Projecao!C:C,MATCH(Dados_Cliente!$B$8*12,Projecao!$A:$A,0)) -> 1300
A9: Cenários de Projeção (percentis 10 / 50 / 90 sobre o retorno da carteira)
A10: Cenário otimista: | B10: =INDEX(Projecao!E:E,MATCH(Dados_Cliente!$B$8*12,Projecao!$A:$A,0)) -> 1397.588
A11: Cenário esperado: | B11: =INDEX(Projecao!D:D,MATCH(Dados_Cliente!$B$8*12,Projecao!$A:$A,0)) -> 1366.2629
A12: Cenário pessimista: | B12: =INDEX(Projecao!F:F,MATCH(Dados_Cliente!$B$8*12,Projecao!$A:$A,0)) -> 1334.5094
A14: Indicadores
A15: Rendimento projetado (cenário esperado) | B15: =B11-B7 -> 66.262904
A16: CAGR (retorno anual composto, cenário esperado) | B16: =(B11/B7)^(1/B6)-1 -> 0.050971464
A17: CAGR real (descontada a inflação) | B17: =(1+B16)/(1+Mercado!B11)-1 -> 0.0057143199
A28: Nota: o gráfico exibe até 30 anos; após o prazo escolhido, as linhas ficam estáveis (o valor não é mais projetado, é apenas mantido para referência visual).

Sheet Projecao
A1: Mês | B1: Ano | C1: Total Aportado | D1: Saldo — Cenário Esperado | E1: Saldo — Cenário Otimista | F1: Saldo — Cenário Pessimista
A2: 0 | B2: 0 | C2: =Dados_Cliente!B6 -> 100 | D2: =Dados_Cliente!B6 -> 100 | E2: =Dados_Cliente!B6 -> 100 | F2: =Dados_Cliente!B6 -> 100
A3: =A2+1 -> 1 | B3: =A3/12 -> 0.083333333 | C3: =IF($A3<=Dados_Cliente!$B$8*12,C2+Dados_Cliente!$B$7,C2) -> 200 | D3: =IF($A3<=Dados_Cliente!$B$8*12,D2*(1+Dados_Cliente!$B$24)+Dados_Cliente!$B$7,D2) -> 200.8241 | E3: =IF($A3<=Dados_Cliente!$B$8*12,E2*(1+Dados_Cliente!$B$27)+Dados_Cliente!$B$7,E2) -> 201.19699 | F3: =IF($A3<=Dados_Cliente!$B$8*12,F2*(1+Dados_Cliente!$B$28)+Dados_Cliente!$B$7,F2) -> 200.4354
A4: =A3+1 -> 2 | B4: =A4/12 -> 0.16666667 | C4: =IF($A4<=Dados_Cliente!$B$8*12,C3+Dados_Cliente!$B$7,C3) -> 300 | D4: =IF($A4<=Dados_Cliente!$B$8*12,D3*(1+Dados_Cliente!$B$24)+Dados_Cliente!$B$7,D3) -> 302.4791 | E4: =IF($A4<=Dados_Cliente!$B$8*12,E3*(1+Dados_Cliente!$B$27)+Dados_Cliente!$B$7,E3) -> 303.60529 | F4: =IF($A4<=Dados_Cliente!$B$8*12,F3*(1+Dados_Cliente!$B$28)+Dados_Cliente!$B$7,F3) -> 301.3081
A5: =A4+1 -> 3 | B5: =A5/12 -> 0.25 | C5: =IF($A5<=Dados_Cliente!$B$8*12,C4+Dados_Cliente!$B$7,C4) -> 400 | D5: =IF($A5<=Dados_Cliente!$B$8*12,D4*(1+Dados_Cliente!$B$24)+Dados_Cliente!$B$7,D4) -> 404.97183 | E5: =IF($A5<=Dados_Cliente!$B$8*12,E4*(1+Dados_Cliente!$B$27)+Dados_Cliente!$B$7,E4) -> 407.2394 | F5: =IF($A5<=Dados_Cliente!$B$8*12,F4*(1+Dados_Cliente!$B$28)+Dados_Cliente!$B$7,F4) -> 402.61999
A6: =A5+1 -> 4 | B6: =A6/12 -> 0.33333333 | C6: =IF($A6<=Dados_Cliente!$B$8*12,C5+Dados_Cliente!$B$7,C5) -> 500 | D6: =IF($A6<=Dados_Cliente!$B$8*12,D5*(1+Dados_Cliente!$B$24)+Dados_Cliente!$B$7,D5) -> 508.30921 | E6: =IF($A6<=Dados_Cliente!$B$8*12,E5*(1+Dados_Cliente!$B$27)+Dados_Cliente!$B$7,E5) -> 512.114 | F6: =IF($A6<=Dados_Cliente!$B$8*12,F5*(1+Dados_Cliente!$B$28)+Dados_Cliente!$B$7,F5) -> 504.373
A7: =A6+1 -> 5 | B7: =A7/12 -> 0.41666667 | C7: =IF($A7<=Dados_Cliente!$B$8*12,C6+Dados_Cliente!$B$7,C6) -> 600 | D7: =IF($A7<=Dados_Cliente!$B$8*12,D6*(1+Dados_Cliente!$B$24)+Dados_Cliente!$B$7,D6) -> 612.4982 | E7: =IF($A7<=Dados_Cliente!$B$8*12,E6*(1+Dados_Cliente!$B$27)+Dados_Cliente!$B$7,E6) -> 618.24394 | F7: =IF($A7<=Dados_Cliente!$B$8*12,F6*(1+Dados_Cliente!$B$28)+Dados_Cliente!$B$7,F6) -> 606.56905
A8: =A7+1 -> 6 | B8: =A8/12 -> 0.5 | C8: =IF($A8<=Dados_Cliente!$B$8*12,C7+Dados_Cliente!$B$7,C7) -> 700 | D8: =IF($A8<=Dados_Cliente!$B$8*12,D7*(1+Dados_Cliente!$B$24)+Dados_Cliente!$B$7,D7) -> 717.54581 | E8: =IF($A8<=Dados_Cliente!$B$8*12,E7*(1+Dados_Cliente!$B$27)+Dados_Cliente!$B$7,E7) -> 725.64424 | F8: =IF($A8<=Dados_Cliente!$B$8*12,F7*(1+Dados_Cliente!$B$28)+Dados_Cliente!$B$7,F7) -> 709.21005
A9: =A8+1 -> 7 | B9: =A9/12 -> 0.58333333 | C9: =IF($A9<=Dados_Cliente!$B$8*12,C8+Dados_Cliente!$B$7,C8) -> 800 | D9: =IF($A9<=Dados_Cliente!$B$8*12,D8*(1+Dados_Cliente!$B$24)+Dados_Cliente!$B$7,D8) -> 823.45911 | E9: =IF($A9<=Dados_Cliente!$B$8*12,E8*(1+Dados_Cliente!$B$27)+Dados_Cliente!$B$7,E8) -> 834.3301 | F9: =IF($A9<=Dados_Cliente!$B$8*12,F8*(1+Dados_Cliente!$B$28)+Dados_Cliente!$B$7,F8) -> 812.29796
A10: =A9+1 -> 8 | B10: =A10/12 -> 0.66666667 | C10: =IF($A10<=Dados_Cliente!$B$8*12,C9+Dados_Cliente!$B$7,C9) -> 900 | D10: =IF($A10<=Dados_Cliente!$B$8*12,D9*(1+Dados_Cliente!$B$24)+Dados_Cliente!$B$7,D9) -> 930.24525 | E10: =IF($A10<=Dados_Cliente!$B$8*12,E9*(1+Dados_Cliente!$B$27)+Dados_Cliente!$B$7,E9) -> 944.31693 | F10: =IF($A10<=Dados_Cliente!$B$8*12,F9*(1+Dados_Cliente!$B$28)+Dados_Cliente!$B$7,F9) -> 915.83471
A11: =A10+1 -> 9 | B11: =A11/12 -> 0.75 | C11: =IF($A11<=Dados_Cliente!$B$8*12,C10+Dados_Cliente!$B$7,C10) -> 1000 | D11: =IF($A11<=Dados_Cliente!$B$8*12,D10*(1+Dados_Cliente!$B$24)+Dados_Cliente!$B$7,D10) -> 1037.9114 | E11: =IF($A11<=Dados_Cliente!$B$8*12,E10*(1+Dados_Cliente!$B$27)+Dados_Cliente!$B$7,E10) -> 1055.6203 | F11: =IF($A11<=Dados_Cliente!$B$8*12,F10*(1+Dados_Cliente!$B$28)+Dados_Cliente!$B$7,F10) -> 1019.8223
A12: =A11+1 -> 10 | B12: =A12/12 -> 0.83333333 | C12: =IF($A12<=Dados_Cliente!$B$8*12,C11+Dados_Cliente!$B$7,C11) -> 1100 | D12: =IF($A12<=Dados_Cliente!$B$8*12,D11*(1+Dados_Cliente!$B$24)+Dados_Cliente!$B$7,D11) -> 1146.4649 | E12: =IF($A12<=Dados_Cliente!$B$8*12,E11*(1+Dados_Cliente!$B$27)+Dados_Cliente!$B$7,E11) -> 1168.2559 | F12: =IF($A12<=Dados_Cliente!$B$8*12,F11*(1+Dados_Cliente!$B$28)+Dados_Cliente!$B$7,F11) -> 1124.2626
A13: =A12+1 -> 11 | B13: =A13/12 -> 0.91666667 | C13: =IF($A13<=Dados_Cliente!$B$8*12,C12+Dados_Cliente!$B$7,C12) -> 1200 | D13: =IF($A13<=Dados_Cliente!$B$8*12,D12*(1+Dados_Cliente!$B$24)+Dados_Cliente!$B$7,D12) -> 1255.9129 | E13: =IF($A13<=Dados_Cliente!$B$8*12,E12*(1+Dados_Cliente!$B$27)+Dados_Cliente!$B$7,E12) -> 1282.2398 | F13: =IF($A13<=Dados_Cliente!$B$8*12,F12*(1+Dados_Cliente!$B$28)+Dados_Cliente!$B$7,F12) -> 1229.1576
A14: =A13+1 -> 12 | B14: =A14/12 -> 1 | C14: =IF($A14<=Dados_Cliente!$B$8*12,C13+Dados_Cliente!$B$7,C13) -> 1300 | D14: =IF($A14<=Dados_Cliente!$B$8*12,D13*(1+Dados_Cliente!$B$24)+Dados_Cliente!$B$7,D13) -> 1366.2629 | E14: =IF($A14<=Dados_Cliente!$B$8*12,E13*(1+Dados_Cliente!$B$27)+Dados_Cliente!$B$7,E13) -> 1397.588 | F14: =IF($A14<=Dados_Cliente!$B$8*12,F13*(1+Dados_Cliente!$B$28)+Dados_Cliente!$B$7,F13) -> 1334.5094
... A362: =A361+1 -> 360 | B362: =A362/12 -> 30 | C362: =IF($A362<=Dados_Cliente!$B$8*12,C361+Dados_Cliente!$B$7,C361) -> 1300 | D362: =IF($A362<=Dados_Cliente!$B$8*12,D361*(1+Dados_Cliente!$B$24)+Dados_Cliente!$B$7,D361) -> 1366.2629 | E362: =IF($A362<=Dados_Cliente!$B$8*12,E361*(1+Dados_Cliente!$B$27)+Dados_Cliente!$B$7,E361) -> 1397.588 | F362: =IF($A362<=Dados_Cliente!$B$8*12,F361*(1+Dados_Cliente!$B$28)+Dados_Cliente!$B$7,F361) -> 1334.5094
